{
  "type": "minecraft:chest",
  "pools": [
    {
      "rolls": {
        "min": 8,
        "max": 16
      },
      "bonus_rolls": 0,
      "entries": [
        {
          "type": "minecraft:item",
          "name": "minecraft:cobweb"
        }
      ]
    },
    {
      "rolls": 3,
      "entries": [
        {
          "type": "minecraft:empty",
          "weight": 15
        },
        {
          "type": "minecraft:item",
          "weight": 35,
          "name": "minecraft:wheat_seeds",
          "functions": [
            {
              "function": "minecraft:set_count",
              "count": {
                "min": 1,
                "max": 8
              }
            }
          ]
        },
        {
          "type": "minecraft:item",
          "weight": 20,
          "name": "minecraft:wheat",
          "functions": [
            {
              "function": "minecraft:set_count",
              "count": {
                "min": 1,
                "max": 4
              }
            }
          ]
        },
        {
          "type": "minecraft:item",
          "weight": 15,
          "name": "minecraft:bone_meal",
          "functions": [
            {
              "function": "minecraft:set_count",
              "count": {
                "min": 1,
                "max": 6
              }
            }
          ]
        },
        {
          "type": "minecraft:item",
          "weight": 5,
          "name": "minecraft:bone_block",
          "functions": [
            {
              "function": "minecraft:set_count",
              "count": {
                "min": 1,
                "max": 2
              }
            }
          ]
        }
      ]
    }
  ]
}
